cloudformation_utils/__init__.py
cloudformation_utils/_version.py
cloudformation_utils-0.0.3.dist-info/licenses/LICENSE
cloudformation_utils-0.0.3.dist-info/METADATA
cloudformation_utils-0.0.3.dist-info/WHEEL
cloudformation_utils-0.0.3.dist-info/top_level.txt
cloudformation_utils-0.0.3.dist-info/RECORD
