Metadata-Version: 2.4
Name: cloudformation-utils
Version: 0.0.3
Summary: A Python library for reading, writing and pre-processing CloudFormation YAML stacks
Author-email: Pasi Niemi <pasi.niemi@nitor.com>
Maintainer-email: Pasi Niemi <pasi.niemi@nitor.com>
License:                                  Apache License
Project-URL: Homepage, https://github.com/NitorCreations/cloudformation-utils
Project-URL: Documentation, https://github.com/NitorCreations/cloudformation-utils
Project-URL: Repository, https://github.com/NitorCreations/cloudformation-utils
Project-URL: Bug Tracker, https://github.com/NitorCreations/cloudformation-utils/issues
Keywords: aws,cloudformation,yaml,infrastructure,devops
Classifier: Development Status :: 5 - Production/Stable
Classifier: Environment :: Other Environment
Classifier: Intended Audience :: Developers
Classifier: Intended Audience :: Information Technology
Classifier: Operating System :: OS Independent
Classifier: Programming Language :: Python
Classifier: Programming Language :: Python :: 3
Classifier: Programming Language :: Python :: 3.8
Classifier: Programming Language :: Python :: 3.9
Classifier: Programming Language :: Python :: 3.10
Classifier: Programming Language :: Python :: 3.11
Classifier: Programming Language :: Python :: 3.12
Classifier: Programming Language :: Python :: 3.13
Classifier: Programming Language :: Python :: Implementation :: CPython
Classifier: Topic :: Software Development :: Libraries :: Python Modules
Classifier: Topic :: System :: Systems Administration
Requires-Python: >=3.8
License-File: LICENSE
Requires-Dist: pyyaml>=6.0
Provides-Extra: test
Requires-Dist: pytest>=7.0; extra == "test"
Requires-Dist: pytest-cov>=4.0; extra == "test"
Requires-Dist: pytest-mock>=3.10; extra == "test"
Requires-Dist: requests-mock>=1.10; extra == "test"
Provides-Extra: dev
Requires-Dist: cloudformation-utils[test]; extra == "dev"
Requires-Dist: build; extra == "dev"
Requires-Dist: twine; extra == "dev"
Requires-Dist: pre-commit; extra == "dev"
Requires-Dist: ruff; extra == "dev"
Requires-Dist: mypy; extra == "dev"
Requires-Dist: types-PyYAML; extra == "dev"
Dynamic: license-file
